flask_interface_gcp_pubsub/__init__.py
flask_interface_gcp_pubsub/__version__.py
flask_interface_gcp_pubsub/publisher.py
flask_interface_gcp_pubsub/pubsub.py
flask_interface_gcp_pubsub/utils.py
flask_interface_gcp_pubsub/view_scheme_async.py
flask_interface_gcp_pubsub/view_scheme_batch.py
tests/unit/__init__.py
tests/unit/test_publisher.py
tests/unit/test_pubsub.py
Flask_InterfacePubSub-0.2.0.dist-info/LICENSE
Flask_InterfacePubSub-0.2.0.dist-info/METADATA
Flask_InterfacePubSub-0.2.0.dist-info/WHEEL
Flask_InterfacePubSub-0.2.0.dist-info/top_level.txt
Flask_InterfacePubSub-0.2.0.dist-info/RECORD
